Metadata-Version: 2.1
Name: texta-lexicon-matcher
Version: 2.0.0
Summary: texta-lexicon-matcher
Home-page: https://git.texta.ee/texta/texta-lexicon-matcher-python
Author: TEXTA
Author-email: info@texta.ee
License: GPLv3
Platform: UNKNOWN
